allauth_extras/admin.py
django_allauth_extras-0.0.2.dist-info/DESCRIPTION.rst
django_allauth_extras-0.0.2.dist-info/METADATA
django_allauth_extras-0.0.2.dist-info/RECORD
django_allauth_extras-0.0.2.dist-info/WHEEL
django_allauth_extras-0.0.2.dist-info/metadata.json
django_allauth_extras-0.0.2.dist-info/top_level.txt
