Metadata-Version: 2.0
Name: django-allauth-extras
Version: 0.0.2
Summary: Various extras for django-allauth package.
Home-page: https://github.com/damoti/django-allauth-extras
Author: Lex Berezhny
Author-email: lex@damoti.com
License: BSD
Keywords: django,auth,authentication,admin
Platform: UNKNOWN
Classifier: Framework :: Django
Classifier: Intended Audience :: Developers
Classifier: License :: OSI Approved :: BSD License
Classifier: Programming Language :: Python :: 3
Classifier: Operating System :: OS Independent
Classifier: Topic :: Software Development :: Libraries :: Python Modules
